paradex_py/__init__.py
paradex_py/constants.py
paradex_py/environment.py
paradex_py/paradex.py
paradex_py/paradex_subkey.py
paradex_py/utils.py
paradex_py/account/__init__.py
paradex_py/account/account.py
paradex_py/account/starknet.py
paradex_py/account/subkey_account.py
paradex_py/account/typed_data.py
paradex_py/account/utils.py
paradex_py/api/__init__.py
paradex_py/api/api_client.py
paradex_py/api/block_trades_api.py
paradex_py/api/http_client.py
paradex_py/api/models.py
paradex_py/api/protocols.py
paradex_py/api/ws_client.py
paradex_py/api/ws_models.py
paradex_py/api/generated/__init__.py
paradex_py/api/generated/requests.py
paradex_py/api/generated/responses.py
paradex_py/common/console_logging.py
paradex_py/common/file_logging.py
paradex_py/common/order.py
paradex_py/message/__init__.py
paradex_py/message/auth.py
paradex_py/message/block_trades.py
paradex_py/message/onboarding.py
paradex_py/message/order.py
paradex_py/message/stark_key.py
paradex_py-0.5.2.dist-info/METADATA
paradex_py-0.5.2.dist-info/WHEEL
paradex_py-0.5.2.dist-info/licenses/LICENSE
paradex_py-0.5.2.dist-info/RECORD
