Metadata-Version: 2.4
Name: paradex_py
Version: 0.5.2
Summary: Paradex Python SDK
Project-URL: Homepage, https://github.com/tradeparadex/paradex-py
Project-URL: Repository, https://github.com/tradeparadex/paradex-py
Project-URL: Documentation, https://tradeparadex.github.io/paradex-py/
Author-email: Paradex <finfo@paradex.trade>
License: MIT License
License-File: LICENSE
Classifier: License :: OSI Approved :: MIT License
Classifier: Operating System :: OS Independent
Classifier: Programming Language :: Python :: 3
Classifier: Programming Language :: Python :: 3.10
Classifier: Programming Language :: Python :: 3.11
Classifier: Programming Language :: Python :: 3.12
Requires-Python: <3.13,>=3.10
Requires-Dist: eth-account<0.12.0,>=0.11.0
Requires-Dist: httpx<0.28.0,>=0.27.0
Requires-Dist: ledgereth<0.10.0,>=0.9.1
Requires-Dist: marshmallow-dataclass<9.0.0,>=8.6.1
Requires-Dist: poseidon-py<0.2.0,>=0.1.0
Requires-Dist: pydantic<3.0.0,>=2.0.0
Requires-Dist: starknet-crypto-py<0.3.0,>=0.2.0
Requires-Dist: starknet-py<0.29.0,>=0.28.0
Requires-Dist: web3<7.0.0,>=6.19.0
Requires-Dist: websockets<16.0,>=15.0
